sqlalchemy_async_seeder/__init__.py
sqlalchemy_async_seeder/base.py
sqlalchemy_async_seeder/builder.py
sqlalchemy_async_seeder/errors.py
sqlalchemy_async_seeder/registry.py
sqlalchemy_async_seeder/resolver.py
sqlalchemy_async_seeder/schema.py
sqlalchemy_async_seeder-0.1.1.dist-info/LICENSE
sqlalchemy_async_seeder-0.1.1.dist-info/WHEEL
sqlalchemy_async_seeder-0.1.1.dist-info/METADATA
sqlalchemy_async_seeder-0.1.1.dist-info/RECORD
